{
  "qa": [
    {
      "q": "من هى اول شهيدة فى الاسلام ؟",
      "a": "أول شهيدة في الإسلام هي الصحابية الجليلة سمية بنت خباط (أم عمار بن ياسر). استشهدت في مكة المكرمة بعد أن عذبها أبو جهل طعناً بحربة، لرفضها ترك دينها، لتكون بذلك أول من استشهد من النساء والرجال، بينما يُعتبر الحارث بن أبي هالة أول شهيد من الرجال في روايات أخرى. "
    },
    { "q": "ما هي أحب الأعمال إلى الله؟", "a": "الصلاة فى وقتها." },
    {
      "q": "ما غراس الجنة؟",
      "a": "سبحان الله والحمد لله ولا إله إلا الله والله أكبر."
    }
  ]
}
